odoo/addons/helpdesk_mgmt_sla/README.rst
odoo/addons/helpdesk_mgmt_sla/__init__.py
odoo/addons/helpdesk_mgmt_sla/__manifest__.py
odoo/addons/helpdesk_mgmt_sla/data/helpdesk_sla_cron.xml
odoo/addons/helpdesk_mgmt_sla/demo/helpdesk_mgmt_sla_demo.xml
odoo/addons/helpdesk_mgmt_sla/i18n/es.po
odoo/addons/helpdesk_mgmt_sla/i18n/helpdesk_mgmt_sla.pot
odoo/addons/helpdesk_mgmt_sla/i18n/pt_BR.po
odoo/addons/helpdesk_mgmt_sla/models/__init__.py
odoo/addons/helpdesk_mgmt_sla/models/helpdesk_sla.py
odoo/addons/helpdesk_mgmt_sla/models/helpdesk_ticket.py
odoo/addons/helpdesk_mgmt_sla/models/helpdesk_ticket_team.py
odoo/addons/helpdesk_mgmt_sla/readme/CONFIGURE.rst
odoo/addons/helpdesk_mgmt_sla/readme/CONTRIBUTORS.rst
odoo/addons/helpdesk_mgmt_sla/readme/DESCRIPTION.rst
odoo/addons/helpdesk_mgmt_sla/readme/USAGE.rst
odoo/addons/helpdesk_mgmt_sla/security/ir.model.access.csv
odoo/addons/helpdesk_mgmt_sla/static/description/icon.png
odoo/addons/helpdesk_mgmt_sla/static/description/index.html
odoo/addons/helpdesk_mgmt_sla/tests/__init__.py
odoo/addons/helpdesk_mgmt_sla/tests/test_helpdesk_mgmt_sla.py
odoo/addons/helpdesk_mgmt_sla/views/helpdesk_sla_views.xml
odoo/addons/helpdesk_mgmt_sla/views/helpdesk_ticket_team_views.xml
odoo/addons/helpdesk_mgmt_sla/views/helpdesk_ticket_views.xml
odoo12_addon_helpdesk_mgmt_sla-12.0.1.0.0.99.dev5.dist-info/METADATA
odoo12_addon_helpdesk_mgmt_sla-12.0.1.0.0.99.dev5.dist-info/WHEEL
odoo12_addon_helpdesk_mgmt_sla-12.0.1.0.0.99.dev5.dist-info/top_level.txt
odoo12_addon_helpdesk_mgmt_sla-12.0.1.0.0.99.dev5.dist-info/RECORD
